protostar_cairo_py-0.1.2.dist-info/METADATA
protostar_cairo_py-0.1.2.dist-info/WHEEL
cairo_python_bindings/__init__.py
cairo_python_bindings/cairo_python_bindings.cpython-39-x86_64-linux-gnu.so
protostar_cairo_py-0.1.2.dist-info/RECORD
