Metadata-Version: 2.1
Name: protostar_cairo_py
Version: 0.1.2
Summary: Protostar Cairo bindings for Python
Project-URL: repository, https://github.com/software-mansion-labs/protostar-cairo-py
